XStatic_Angular_Bootstrap-2.5.0.0-py3.6-nspkg.pth
xstatic/pkg/angular_bootstrap/__init__.py
xstatic/pkg/angular_bootstrap/data/angular-bootstrap.js
XStatic_Angular_Bootstrap-2.5.0.0.dist-info/LICENSE
XStatic_Angular_Bootstrap-2.5.0.0.dist-info/METADATA
XStatic_Angular_Bootstrap-2.5.0.0.dist-info/WHEEL
XStatic_Angular_Bootstrap-2.5.0.0.dist-info/namespace_packages.txt
XStatic_Angular_Bootstrap-2.5.0.0.dist-info/top_level.txt
XStatic_Angular_Bootstrap-2.5.0.0.dist-info/RECORD
