Metadata-Version: 2.1
Name: XStatic-Angular-Bootstrap
Version: 2.5.0.0
Summary: Angular-Bootstrap 2.5.0 (XStatic packaging standard)
Home-page: http://angular-ui.github.io/bootstrap/
Maintainer: Radomir Dopieralski
Maintainer-email: openstack@sheep.art.pl
License: MIT
Keywords: angular_bootstrap xstatic
Platform: any
